{
  "name": "lich_spawn_pool",
  "effects": [
    {
      "type": "add_entities",
      "entities": [
        {
          "weight": 10,
          "type": "lich",
          "overrides": {
            "name": "Ry'Ga",
            "description": "",
            "tags": [],
            "components": [
              {
                "type": "ai"
              }
            ],
            "actions": [],
            "classes": [
              {
                "class": "necromancer",
                "level": 6
              }
            ]
          }
        }
      ],
      "amount": 1,
      "target": 0
    }
  ],
  "conditions": [],
  "restrictions": {
    "required": [
      "mini_boss_room"
    ],
    "allowed": [],
    "excluded": []
  }
}
